backaind/__init__.py
backaind/aifile.py
backaind/ainteraction.py
backaind/auth.py
backaind/brain.py
backaind/extensions.py
backaind/knowledge.py
backaind/models.py
backaind/settings.py
backaind/workshop.py
backaind/api/__init__.py
backaind/api/ai.py
backaind/api/knowledge.py
backaind/static/ownai-ainteraction.css
backaind/static/ownai-ainteraction.js
backaind/static/ownai-main.css
backaind/static/ownai-main.js
backaind/static/ownai-workshop.css
backaind/static/ownai-workshop.js
backaind/static/assets/_plugin-vue_export-helper-11cccb1d.js
backaind/static/assets/bootstrap.esm-756fae2f.js
backaind/templates/base.html
backaind/templates/_includes/main_menu.html
backaind/templates/_includes/user_menu.html
backaind/templates/_macros/assets.html
backaind/templates/ainteraction/index.html
backaind/templates/auth/login.html
backaind/templates/settings/external_providers.html
backaind/templates/settings/password.html
backaind/templates/workshop/ai.html
backaind/templates/workshop/knowledge.html
migrations/env.py
migrations/versions/1328ef37e5dc_initial_table_setup.py
migrations/versions/16c3aa6e11aa_add_greeting_and_input_labels_columns.py
migrations/versions/3dba1ccfa13d_add_public_ais_and_knowledge.py
migrations/versions/58ae6bdf9d33_rename_settings_table.py
ownAI-0.4.0.dist-info/LICENSE.txt
ownAI-0.4.0.dist-info/METADATA
ownAI-0.4.0.dist-info/WHEEL
ownAI-0.4.0.dist-info/top_level.txt
ownAI-0.4.0.dist-info/RECORD
