Metadata-Version: 2.1
Name: ownAI
Version: 0.4.0
Summary: Run your own AI
Home-page: https://ownai.org
License: MIT
License-File: LICENSE.txt
Requires-Dist: flask
Requires-Dist: flask-socketio
Requires-Dist: Flask-SQLAlchemy
Requires-Dist: Flask-Migrate
Requires-Dist: langchain
